[ {
  "objectIndex" : "25",
  "property" : "dbp:stateHouse",
  "object" : "North Carolina",
  "distribution" : [ {
    "probabilities" : {
      "probability(state|North Carolina)" : 0.8783783784,
      "probability(North Carolina|state)" : 0.4482758621
    }
  }, {
    "probabilities" : {
      "probability(district|North Carolina)" : 0.9594594595,
      "probability(North Carolina|district)" : 0.4034090909
    }
  }, {
    "probabilities" : {
      "probability(term|North Carolina)" : 0.5540540541,
      "probability(North Carolina|term)" : 0.5694444444
    }
  }, {
    "probabilities" : {
      "probability(democratic|North Carolina)" : 0.5810810811,
      "probability(North Carolina|democratic)" : 0.5
    }
  }, {
    "probabilities" : {
      "probability(retired|North Carolina)" : 0.2432432432,
      "probability(North Carolina|retired)" : 0.9
    }
  }, {
    "probabilities" : {
      "probability(county|North Carolina)" : 0.4189189189,
      "probability(North Carolina|county)" : 0.4492753623
    }
  }, {
    "probabilities" : {
      "probability(republican|North Carolina)" : 0.3918918919,
      "probability(North Carolina|republican)" : 0.2959183673
    }
  }, {
    "probabilities" : {
      "probability(session|North Carolina)" : 0.1891891892,
      "probability(North Carolina|session)" : 0.5833333333
    }
  }, {
    "probabilities" : {
      "probability(first|North Carolina)" : 0.2297297297,
      "probability(North Carolina|first)" : 0.3541666667
    }
  }, {
    "probabilities" : {
      "probability(election|North Carolina)" : 0.2432432432,
      "probability(North Carolina|election)" : 0.3050847458
    }
  }, {
    "probabilities" : {
      "probability(former|North Carolina)" : 0.2162162162,
      "probability(North Carolina|former)" : 0.32
    }
  }, {
    "probabilities" : {
      "probability(primary|North Carolina)" : 0.1351351351,
      "probability(North Carolina|primary)" : 0.4761904762
    }
  }, {
    "probabilities" : {
      "probability(office|North Carolina)" : 0.1486486486,
      "probability(North Carolina|office)" : 0.3666666667
    }
  }, {
    "probabilities" : {
      "probability(part|North Carolina)" : 0.1756756757,
      "probability(North Carolina|part)" : 0.1780821918
    }
  }, {
    "probabilities" : {
      "probability(american|North Carolina)" : 0.1621621622,
      "probability(North Carolina|american)" : 0.16
    }
  }, {
    "probabilities" : {
      "probability(legislative|North Carolina)" : 0.0945945946,
      "probability(North Carolina|legislative)" : 0.2692307692
    }
  }, {
    "probabilities" : {
      "probability(seat|North Carolina)" : 0.0810810811,
      "probability(North Carolina|seat)" : 0.2727272727
    }
  } ]
} ]